odoo/addons/account_cash_discount_write_off/README.rst
odoo/addons/account_cash_discount_write_off/__init__.py
odoo/addons/account_cash_discount_write_off/__manifest__.py
odoo/addons/account_cash_discount_write_off/i18n/account_cash_discount_write_off.pot
odoo/addons/account_cash_discount_write_off/i18n/es.po
odoo/addons/account_cash_discount_write_off/i18n/fr.po
odoo/addons/account_cash_discount_write_off/i18n/it.po
odoo/addons/account_cash_discount_write_off/models/__init__.py
odoo/addons/account_cash_discount_write_off/models/account_payment_line.py
odoo/addons/account_cash_discount_write_off/models/account_payment_order.py
odoo/addons/account_cash_discount_write_off/models/res_company.py
odoo/addons/account_cash_discount_write_off/readme/CONFIGURATION.rst
odoo/addons/account_cash_discount_write_off/readme/CONTRIBUTORS.rst
odoo/addons/account_cash_discount_write_off/readme/DESCRIPTION.rst
odoo/addons/account_cash_discount_write_off/readme/USAGE.rst
odoo/addons/account_cash_discount_write_off/static/description/icon.png
odoo/addons/account_cash_discount_write_off/static/description/index.html
odoo/addons/account_cash_discount_write_off/tests/__init__.py
odoo/addons/account_cash_discount_write_off/tests/test_account_cash_discount_write_off.py
odoo/addons/account_cash_discount_write_off/views/res_company.xml
odoo14_addon_account_cash_discount_write_off-14.0.1.0.1.dev10.dist-info/METADATA
odoo14_addon_account_cash_discount_write_off-14.0.1.0.1.dev10.dist-info/WHEEL
odoo14_addon_account_cash_discount_write_off-14.0.1.0.1.dev10.dist-info/top_level.txt
odoo14_addon_account_cash_discount_write_off-14.0.1.0.1.dev10.dist-info/RECORD
